frpy/__init__.py
frpy/builder/__init__.py
frpy/builder/track.py
frpy/client/Client.py
frpy/client/__init__.py
frpy/client/base_client.py
frpy/managers/__init__.py
frpy/managers/base_manager.py
frpy/managers/client_friend_manager.py
frpy/managers/comment_manager.py
frpy/managers/cosmetic_manager.py
frpy/managers/friend_manager.py
frpy/managers/friend_request_manager.py
frpy/managers/notification_manager.py
frpy/managers/race_manager.py
frpy/managers/track_manager.py
frpy/managers/user_manager.py
frpy/rest/__init__.py
frpy/rest/constants.py
frpy/rest/endpoints.py
frpy/rest/exceptions.py
frpy/rest/request_handler.py
frpy/structures/Comment.py
frpy/structures/Cosmetic.py
frpy/structures/Notification.py
frpy/structures/Race.py
frpy/structures/Track.py
frpy/structures/User.py
frpy/structures/__init__.py
frpy/structures/base.py
frpy/structures/base_structure.py
frpy/structures/client_user.py
frpy/structures/friend_request.py
frpy/utils/Events.py
frpy/utils/Map.py
frpy/utils/__init__.py
frpy/utils/event_emitter.py
frpy/utils/t2t.py
frpy-0.3.1.dist-info/licenses/LICENSE
frpy-0.3.1.dist-info/METADATA
frpy-0.3.1.dist-info/WHEEL
frpy-0.3.1.dist-info/top_level.txt
frpy-0.3.1.dist-info/RECORD
