Metadata-Version: 2.4
Name: frpy
Version: 0.3.1
Summary: An api wrapper for Free Rider HD
Home-page: https://github.com/Calculamatrise/frpy
Author: Calculamatrise
License: GPL-3.0 license
Project-URL: Source, https://github.com/Calculamatrise/frpy
Project-URL: Bug Tracker, https://github.com/Calculamatrise/frpy/issues
Keywords: api,bot,frhd,frhd-api,freeriderhd,freeriderhd-api
Classifier: Intended Audience :: Developers
Classifier: Programming Language :: Python :: 3
Classifier: Programming Language :: Python :: 3.8
Classifier: Programming Language :: Python :: 3.9
Classifier: Programming Language :: Python :: 3.10
Classifier: Programming Language :: Python :: 3.11
Classifier: Programming Language :: Python :: 3.12
Classifier: License :: OSI Approved :: GNU General Public License v3 (GPLv3)
Requires-Python: >=3.8
License-File: LICENSE
Requires-Dist: requests
Dynamic: author
Dynamic: classifier
Dynamic: description
Dynamic: description-content-type
Dynamic: home-page
Dynamic: keywords
Dynamic: license
Dynamic: license-file
Dynamic: project-url
Dynamic: requires-dist
Dynamic: requires-python
Dynamic: summary
